project_storm/__init__.py
project_storm/get_ws.py
project_storm/getconfig.py
project_storm/ggs_stuff.py
project_storm/just_funcs.py
project_storm/pstorm.py
project_storm/server_list.json
project_storm-1.0.3.dist-info/METADATA
project_storm-1.0.3.dist-info/WHEEL
project_storm-1.0.3.dist-info/top_level.txt
project_storm-1.0.3.dist-info/RECORD
