Metadata-Version: 2.4
Name: project-storm
Version: 1.0.3
Summary: Python library to interact with Goodgame Empire websocket server.
Author-email: WojtS & ThunderStorm <wojts8@proton.me>
Project-URL: Homepage, https://github.com/wojtsik/brunogge
Requires-Python: >=3.12
Requires-Dist: websockets==13.1
Requires-Dist: requests
Requires-Dist: packaging
Requires-Dist: schedule
Requires-Dist: playwright
